{"id":"5u2uiaco359415r2i31ymac","title":"Methods","desc":"","updated":1718557791270,"created":1718349372688,"custom":{},"fname":"Master-Works.Edouard-Brülhart.Methods","type":"note","vault":{"fsPath":"vault"},"contentHash":"2c4dac2dd9720a3c0d5183e7474bc23e","links":[{"type":"wiki","from":{"fname":"Master-Works.Edouard-Brülhart.Methods","id":"5u2uiaco359415r2i31ymac","vaultName":"vault"},"value":"Master-Works.Edouard-Brülhart.Database","position":{"start":{"line":3,"column":5,"offset":102},"end":{"line":3,"column":47,"offset":144},"indent":[]},"xvault":false,"sameFile":false,"to":{"fname":"Master-Works.Edouard-Brülhart.Database"}},{"type":"wiki","from":{"fname":"Master-Works.Edouard-Brülhart.Methods","id":"5u2uiaco359415r2i31ymac","vaultName":"vault"},"value":"Master-Works.Edouard-Brülhart.Collection","position":{"start":{"line":5,"column":5,"offset":150},"end":{"line":5,"column":49,"offset":194},"indent":[]},"xvault":false,"sameFile":false,"to":{"fname":"Master-Works.Edouard-Brülhart.Collection"}},{"type":"wiki","from":{"fname":"Master-Works.Edouard-Brülhart.Methods","id":"5u2uiaco359415r2i31ymac","vaultName":"vault"},"value":"Master-Works.Edouard-Brülhart.Laboratory","position":{"start":{"line":7,"column":5,"offset":200},"end":{"line":7,"column":49,"offset":244},"indent":[]},"xvault":false,"sameFile":false,"to":{"fname":"Master-Works.Edouard-Brülhart.Laboratory"}},{"type":"wiki","from":{"fname":"Master-Works.Edouard-Brülhart.Methods","id":"5u2uiaco359415r2i31ymac","vaultName":"vault"},"value":"Master-Works.Edouard-Brülhart.Mass spectrometry","position":{"start":{"line":10,"column":5,"offset":251},"end":{"line":10,"column":56,"offset":302},"indent":[]},"xvault":false,"sameFile":false,"to":{"fname":"Master-Works.Edouard-Brülhart.Mass spectrometry"}},{"from":{"fname":"Master-Works.Edouard-Brülhart","id":"b4lvd0q7xo9b1z98xth6zjq","vaultName":"vault"},"type":"backlink","position":{"start":{"line":12,"column":4,"offset":496},"end":{"line":12,"column":45,"offset":537},"indent":[]},"value":"Master-Works.Edouard-Brülhart.Methods"}],"anchors":{"":{"type":"header","text":"","value":"","line":9,"column":0,"depth":3},"-1":{"type":"header","text":"","value":"-1","line":11,"column":0,"depth":3},"-2":{"type":"header","text":"","value":"-2","line":13,"column":0,"depth":3},"-3":{"type":"header","text":"","value":"-3","line":16,"column":0,"depth":3}},"children":[],"parent":"b4lvd0q7xo9b1z98xth6zjq","data":{}}
