{"id":"9doklqvi0ouralfpxr5gukv","title":"QGIS","desc":"","updated":1718371989979,"created":1718371989979,"custom":{},"fname":"Services.QGIS","type":"note","vault":{"fsPath":"vault"},"contentHash":"41f26e09b7fcfce3b0907eb697e0466d","links":[{"from":{"fname":"Services.QGIS.DBGI-plugin","id":"1u37mlza55e6dgksabcv7qn","vaultName":"vault"},"type":"backlink","position":{"start":{"line":35,"column":1,"offset":2214},"end":{"line":35,"column":18,"offset":2231},"indent":[]},"value":"Services.QGIS"}],"anchors":{},"children":["1u37mlza55e6dgksabcv7qn"],"parent":"vphzpqwuu98x8sfgfrconej","data":{}}
