{"fname":"workshops.2023","stub":true,"vault":{"fsPath":"vault"},"schemaStub":false,"type":"note","updated":1742541881359,"created":1742541881359,"id":"9g1earpb1pavdmi87nxhfmt","desc":"","links":[{"from":{"fname":"open-notebook.dbgi.pmallard.2023.07.06","id":"0a3imv12qpz8x053ojqpj66","vaultName":"vault"},"type":"backlink","position":{"start":{"line":18,"column":1,"offset":263},"end":{"line":18,"column":19,"offset":281},"indent":[]},"value":"workshops.2023"}],"anchors":{},"children":["sdturd4n06yzolf5u0xu3yv","u673zctxvpmbkafg9ikey6g"],"parent":"tcczzuydjsyb9b1f4k4pe45","data":{},"title":"2023"}
