{"id":"bu0nndv79i0j85ewpg66wmu","title":"2023-03-17","desc":"","updated":1679048108728,"created":1679044375359,"traitIds":["open-notebook-ebruelhart"],"custom":{},"fname":"open-notebook.dbgi.ebruelhart.2023.03.17","type":"note","vault":{"fsPath":"vault"},"contentHash":"85580e359d14ca0b74bc0829229c256c","links":[],"anchors":{"this-is-edouards-dbgi-daily-open-notebook":{"type":"header","text":"This is Edouard's DBGI daily open-notebook.","value":"this-is-edouards-dbgi-daily-open-notebook","line":10,"column":0,"depth":1}},"children":[],"parent":"w2q3rxrnen414sj14n7uob6","data":{}}
