{"id":"h0tefctxts86anr2vsfp89x","title":"_a","desc":"","updated":1656059639672,"created":1656059639672,"isDir":false,"custom":{"isDir":false},"fname":"Bachelor-Works.Edouard-Brülhart.biblio._a","type":"note","vault":{"fsPath":"vault"},"contentHash":"5fa256a27a70569a5c0dbb1e2e389c2b","links":[{"type":"wiki","from":{"fname":"Bachelor-Works.Edouard-Brülhart.biblio._a","id":"h0tefctxts86anr2vsfp89x","vaultName":"vault"},"value":"webpage","position":{"start":{"line":5,"column":14,"offset":89},"end":{"line":5,"column":25,"offset":100},"indent":[]},"xvault":false,"sameFile":false,"to":{"fname":"webpage"}},{"type":"wiki","from":{"fname":"Bachelor-Works.Edouard-Brülhart.biblio._a","id":"h0tefctxts86anr2vsfp89x","vaultName":"vault"},"value":"2022-03-31","position":{"start":{"line":6,"column":15,"offset":115},"end":{"line":6,"column":29,"offset":129},"indent":[]},"xvault":false,"sameFile":false,"to":{"fname":"2022-03-31"}},{"type":"wiki","from":{"fname":"Bachelor-Works.Edouard-Brülhart.biblio._a","id":"h0tefctxts86anr2vsfp89x","vaultName":"vault"},"value":"gnss-location","position":{"start":{"line":9,"column":11,"offset":211},"end":{"line":9,"column":28,"offset":228},"indent":[]},"xvault":false,"sameFile":false,"to":{"fname":"gnss-location"}},{"type":"wiki","from":{"fname":"Bachelor-Works.Edouard-Brülhart.biblio._a","id":"h0tefctxts86anr2vsfp89x","vaultName":"vault"},"value":"tags.zotero","alias":"#zotero","position":{"start":{"line":10,"column":3,"offset":231},"end":{"line":10,"column":10,"offset":238},"indent":[]},"xvault":false,"to":{"fname":"tags.zotero"}},{"type":"wiki","from":{"fname":"Bachelor-Works.Edouard-Brülhart.biblio._a","id":"h0tefctxts86anr2vsfp89x","vaultName":"vault"},"value":"tags.literature-notes","alias":"#literature-notes","position":{"start":{"line":10,"column":12,"offset":240},"end":{"line":10,"column":29,"offset":257},"indent":[]},"xvault":false,"to":{"fname":"tags.literature-notes"}},{"type":"wiki","from":{"fname":"Bachelor-Works.Edouard-Brülhart.biblio._a","id":"h0tefctxts86anr2vsfp89x","vaultName":"vault"},"value":"tags.reference","alias":"#reference","position":{"start":{"line":10,"column":31,"offset":259},"end":{"line":10,"column":41,"offset":269},"indent":[]},"xvault":false,"to":{"fname":"tags.reference"}}],"anchors":{"rtklib-an-open-source-program-package-for-gnss-positioning":{"type":"header","text":"RTKLIB: An Open Source Program Package for GNSS Positioning","value":"rtklib-an-open-source-program-package-for-gnss-positioning","line":8,"column":0,"depth":1},"metadata":{"type":"header","text":"Metadata","value":"metadata","line":10,"column":0,"depth":2},"zotero-links":{"type":"header","text":"Zotero links","value":"zotero-links","line":20,"column":0,"depth":2}},"children":[],"parent":"z1zl1fl62r0zie9azb8ejhm","data":{}}
