{"fname":"open-notebook.dbgi.pmallard.2023.03","stub":true,"vault":{"fsPath":"vault"},"schemaStub":false,"type":"note","updated":1739900862829,"created":1739900862829,"id":"hb42iuq17odmuy6bqwuaeys","desc":"","links":[],"anchors":{},"children":["bo108ix90a9ywbkbgtghxym","d68hrdr6hfb2cin8tpzpivq","5e8mwuzcvsa1op9fd5apt8e","8ydxt86g2zi3p99fraumr29","ihhg3osvy26wih9yn07tewx","za219ohh6orf6x1y7fvrkxh","kce3yv1v6lcse3zuvmb9hfz","dfj04lm9swzeg51xcbpgt5v"],"parent":"4n42fzh0f4ribap4g6uzakd","data":{},"title":"03"}
