{"id":"kic43cz8oqcqxoig3px4gs1","title":"2024-06-13","desc":"","updated":1718263989720,"created":1718263802462,"traitIds":["open-notebook-dbgi-ebruelhart"],"custom":{},"fname":"open-notebook.dbgi.ebruelhart.2024.06.13","type":"note","vault":{"fsPath":"vault"},"contentHash":"ac5e550dcfd0fa846083ad80ae03cef0","links":[],"anchors":{"this-is-edouards-dbgi-daily-open-notebook":{"type":"header","text":"This is Edouard's DBGI daily open-notebook.","value":"this-is-edouards-dbgi-daily-open-notebook","line":9,"column":0,"depth":1},"to-do-for-presentationmanuscript":{"type":"header","text":"To do for presentation/manuscript","value":"to-do-for-presentationmanuscript","line":13,"column":0,"depth":1},"done":{"type":"header","text":"done","value":"done","line":22,"column":0,"depth":1},"perspectives":{"type":"header","text":"Perspectives","value":"perspectives","line":24,"column":0,"depth":1},"notes":{"type":"header","text":"notes","value":"notes","line":26,"column":0,"depth":1},"code":{"type":"header","text":"code","value":"code","line":28,"column":0,"depth":1},"links":{"type":"header","text":"links","value":"links","line":30,"column":0,"depth":1}},"children":[],"parent":"xkd72n4wsx76xjs8335h9xe","data":{}}
