{"id":"q4tfhn8lnlx20enhro8ly4y","title":"Daily Journal Template","desc":"","updated":1687273878211,"created":1687273878211,"custom":{},"fname":"templates.daily","type":"note","vault":{"fsPath":"vault"},"contentHash":"91a670ca2234c040e1e3810a69a8d86b","links":[{"type":"wiki","from":{"fname":"templates.daily","id":"q4tfhn8lnlx20enhro8ly4y","vaultName":"vault"},"value":"templates.daily","position":{"start":{"line":1,"column":68,"offset":67},"end":{"line":1,"column":87,"offset":86},"indent":[]},"xvault":false,"sameFile":false,"to":{"fname":"templates.daily"}},{"from":{"fname":"templates.daily","id":"q4tfhn8lnlx20enhro8ly4y","vaultName":"vault"},"type":"backlink","position":{"start":{"line":1,"column":68,"offset":67},"end":{"line":1,"column":87,"offset":86},"indent":[]},"value":"templates.daily"}],"anchors":{"morning":{"type":"header","text":"Morning","value":"morning","line":16,"column":0,"depth":2},"gratitude":{"type":"header","text":"Gratitude","value":"gratitude","line":20,"column":0,"depth":3},"what-would-make-today-great":{"type":"header","text":"What would make today great?","value":"what-would-make-today-great","line":28,"column":0,"depth":3},"daily-affirmations":{"type":"header","text":"Daily affirmations","value":"daily-affirmations","line":34,"column":0,"depth":3},"evening":{"type":"header","text":"Evening","value":"evening","line":38,"column":0,"depth":2},"amazing-things-that-happened-today":{"type":"header","text":"Amazing things that happened today","value":"amazing-things-that-happened-today","line":42,"column":0,"depth":3},"how-could-i-have-made-today-even-better":{"type":"header","text":"How could I have made today even better?","value":"how-could-i-have-made-today-even-better","line":48,"column":0,"depth":3}},"children":[],"parent":"h8trx40s491czjp1npypo68","data":{}}
