{"fname":"open-notebook.dbgi.alecabec.2023.06","stub":true,"vault":{"fsPath":"vault"},"schemaStub":false,"type":"note","updated":1743321942394,"created":1743321942394,"id":"sgcxe12c2ex4kynb9h2p2uq","desc":"","links":[],"anchors":{},"children":["9f3q0f4mb6290b4topikcz1","at1rofti4wm05hfdlfi8vie","9jnk8rctu6gz3arc5v1lom0","uc5kxcbfvli6vk0z9x1b2mb","5ikmb6qdj2x03braqx4tjcp","aekrrxb8bzhzb2kce0virw4","2s1vp8k62157g34s0gbtwqg","ialf7d4ig1b2fapedzvbxbb"],"parent":"luwj0u3v1ndqytgujubxev8","data":{},"title":"06"}
