{"id":"u6onqx095u4r2pji608uku0","title":"2022-02-28","desc":"","updated":1655027552109,"created":1646035368686,"traitIds":["journalNote"],"custom":{},"fname":"open-notebook.dbgi.ebruelhart.2022.02.28","type":"note","vault":{"fsPath":"vault"},"contentHash":"c296a9c8ded3b4c2fe7cfc4a448cc773","links":[],"anchors":{"starting-the-day":{"type":"header","text":"Starting the day","value":"starting-the-day","line":11,"column":0,"depth":2},"todays-todo":{"type":"header","text":"Today's Todo","value":"todays-todo","line":15,"column":0,"depth":3},"today-notes--ideas":{"type":"header","text":"Today Notes & ideas","value":"today-notes--ideas","line":21,"column":0,"depth":3},"ending-the-day":{"type":"header","text":"Ending the day","value":"ending-the-day","line":26,"column":0,"depth":2},"future-todo":{"type":"header","text":"Future Todo","value":"future-todo","line":28,"column":0,"depth":3}},"children":[],"parent":"umn29zblq45ou3n4vqhugqe","data":{}}
